readcqt/__init__.py
readcqt/_data_frame_preparer.py
readcqt/_sheet_filter.py
readcqt/config.py
readcqt-1.1.3.dist-info/WHEEL
readcqt-1.1.3.dist-info/METADATA
readcqt-1.1.3.dist-info/RECORD
