Metadata-Version: 2.1
Name: readcqt
Version: 1.1.3
Summary: Converts specification from .xlsx files into a dataframe.
License: WTFPL
Author: Sergey Belousov
Requires-Python: >=3.8,<4.0
Classifier: License :: Other/Proprietary License
Classifier: Programming Language :: Python :: 3
Classifier: Programming Language :: Python :: 3.8
Classifier: Programming Language :: Python :: 3.9
Requires-Dist: pandas (>=1.1.4,<2.0.0)
Requires-Dist: tabulate (>=0.8.7,<0.9.0)
